llm_bridge_mcp/__init__.py
llm_bridge_mcp/main.py
llm_bridge_mcp-0.1.2.dist-info/METADATA
llm_bridge_mcp-0.1.2.dist-info/WHEEL
llm_bridge_mcp-0.1.2.dist-info/entry_points.txt
llm_bridge_mcp-0.1.2.dist-info/licenses/LICENSE
llm_bridge_mcp-0.1.2.dist-info/RECORD
