Metadata-Version: 2.4
Name: llm_bridge_mcp
Version: 0.1.2
Summary: A simple MCP server that provides a unified interface to various LLM providers using Pydantic AI
License-File: LICENSE
Requires-Python: >=3.11
Requires-Dist: mcp[cli]>=0.1.0
Requires-Dist: pydantic-ai>=0.0.39
Requires-Dist: pydantic>=2.10.6
Requires-Dist: python-dotenv>=1.0.0
